lidar_visualizer/__init__.py
lidar_visualizer/lidar_visualizer.py
lidar_visualizer/visualizer.py
lidar_visualizer/datasets/__init__.py
lidar_visualizer/datasets/generic.py
lidar_visualizer/datasets/helipr.py
lidar_visualizer/datasets/mcap.py
lidar_visualizer/datasets/ouster.py
lidar_visualizer/datasets/point_cloud2.py
lidar_visualizer/datasets/rosbag.py
lidar_visualizer-0.1.4.dist-info/LICENSE
lidar_visualizer-0.1.4.dist-info/METADATA
lidar_visualizer-0.1.4.dist-info/WHEEL
lidar_visualizer-0.1.4.dist-info/entry_points.txt
lidar_visualizer-0.1.4.dist-info/top_level.txt
lidar_visualizer-0.1.4.dist-info/RECORD
