Metadata-Version: 2.1
Name: lidar_visualizer
Version: 0.1.4
Summary: A LiDAR visualization tool for all your datasets
Author-email: Ignacio Vizzo <ignaciovizzo@gmail.com>
License: MIT License
Project-URL: homepage, https://github.com/PRBonn/lidar-visualizer
Keywords: LiDAR,Robotics,Visualization
Classifier: Operating System :: Unix
Classifier: Operating System :: MacOS
Classifier: Operating System :: Microsoft :: Windows
Classifier: Programming Language :: C++
Classifier: Programming Language :: Python :: 3
Classifier: Programming Language :: Python :: 3.7
Classifier: Programming Language :: Python :: 3.8
Classifier: Programming Language :: Python :: 3.9
Classifier: Programming Language :: Python :: 3.10
Classifier: Programming Language :: Python :: 3.11
Classifier: Intended Audience :: Developers
Classifier: Intended Audience :: Education
Classifier: Intended Audience :: Other Audience
Classifier: Intended Audience :: Science/Research
Classifier: License :: OSI Approved :: MIT License
Requires-Python: >=3.7
License-File: LICENSE
Requires-Dist: natsort
Requires-Dist: numpy
Requires-Dist: tqdm
Requires-Dist: polyscope >=2.2.1
Requires-Dist: typer[all] >=0.6.0
Provides-Extra: all
Requires-Dist: pyntcloud ; extra == 'all'
Requires-Dist: trimesh ; extra == 'all'
Requires-Dist: ouster-sdk ; extra == 'all'
